openinference/instrumentation/monkai_agent/__init__.py
openinference/instrumentation/monkai_agent/_wrappers.py
openinference/instrumentation/monkai_agent/version.py
openinference_instrumentation_monkai_agent-0.0.1.dist-info/METADATA
openinference_instrumentation_monkai_agent-0.0.1.dist-info/WHEEL
openinference_instrumentation_monkai_agent-0.0.1.dist-info/entry_points.txt
openinference_instrumentation_monkai_agent-0.0.1.dist-info/licenses/LICENSE
openinference_instrumentation_monkai_agent-0.0.1.dist-info/RECORD
