Metadata-Version: 2.4
Name: openinference-instrumentation-monkai-agent
Version: 0.0.1
Summary: OpenInference instrumentation for MonkAI Agent
Author: MonkAI Team
License-Expression: MIT
License-File: LICENSE
Requires-Python: >=3.10
Requires-Dist: monkai-agent>=0.0.33
Requires-Dist: opentelemetry-api>=1.0.0
Requires-Dist: opentelemetry-instrumentation>=0.37b0
Requires-Dist: wrapt>=1.11.2
